cwm/__init__.py
cwm/ask_cmd.py
cwm/bank_cmd.py
cwm/clear_cmd.py
cwm/cli.py
cwm/config_cmd.py
cwm/copy_cmd.py
cwm/file_mapper.py
cwm/get_cmd.py
cwm/git_cmd.py
cwm/git_utils.py
cwm/group_cmd.py
cwm/jump_cmd.py
cwm/project_cmd.py
cwm/project_utils.py
cwm/rich_help.py
cwm/run_cmd.py
cwm/save_cmd.py
cwm/schema_validator.py
cwm/service_manager.py
cwm/setup_cmd.py
cwm/shell_hook.py
cwm/storage_manager.py
cwm/utils.py
cwm/watch_cmd.py
cwm/gui/__init__.py
cwm/gui/logo.png
cwm/gui/tk_app.py
cwm_cli-2.1.0.dist-info/METADATA
cwm_cli-2.1.0.dist-info/WHEEL
cwm_cli-2.1.0.dist-info/entry_points.txt
cwm_cli-2.1.0.dist-info/licenses/LICENSE
cwm_cli-2.1.0.dist-info/RECORD
