Metadata-Version: 2.4
Name: cwm-cli
Version: 2.1.0
Summary: Command Watch Manager - Workspace, History, and AI Assistant for Developers.
Project-URL: Homepage, https://github.com/Isu-Ismail/cwm
Project-URL: Bug Tracker, https://github.com/Isu-Ismail/cwm/issues
Project-URL: Documentation Page, https://isu-ismail.github.io/cwm-docwebsite/index.html
Author-email: Ismail <ismailisims1@gmail.com>
License-Expression: MIT
License-File: LICENSE
Keywords: ai,cli,git,history,manager,productivity,terminal,workspace
Classifier: Development Status :: 4 - Beta
Classifier: Intended Audience :: Developers
Classifier: Operating System :: OS Independent
Classifier: Programming Language :: Python :: 3
Classifier: Topic :: Utilities
Requires-Python: >=3.8
Requires-Dist: click
Requires-Dist: colorama
Requires-Dist: pathspec
Requires-Dist: prompt-toolkit
Requires-Dist: psutil
Requires-Dist: pyperclip
Requires-Dist: rich
Provides-Extra: ai
Requires-Dist: google-genai; extra == 'ai'
Requires-Dist: ollama; extra == 'ai'
Requires-Dist: openai; extra == 'ai'
